dash_cytoscape/CyLeaflet.py
dash_cytoscape/Cytoscape.py
dash_cytoscape/__init__.py
dash_cytoscape/_imports_.py
dash_cytoscape/dash_cytoscape.dev.js
dash_cytoscape/dash_cytoscape.min.js
dash_cytoscape/dash_cytoscape_extra.dev.js
dash_cytoscape/dash_cytoscape_extra.min.js
dash_cytoscape/metadata.json
dash_cytoscape/package.json
dash_cytoscape/utils/Tree.py
dash_cytoscape/utils/__init__.py
dash_cytoscape-1.0.0.dist-info/LICENSE
dash_cytoscape-1.0.0.dist-info/METADATA
dash_cytoscape-1.0.0.dist-info/WHEEL
dash_cytoscape-1.0.0.dist-info/top_level.txt
dash_cytoscape-1.0.0.dist-info/RECORD
