Metadata-Version: 2.1
Name: dash-cytoscape
Version: 1.0.0
Summary: A Component Library for Dash aimed at facilitating network visualization in Python, wrapped around Cytoscape.js
Home-page: https://dash.plotly.com/cytoscape
Author: The Plotly Team <cytoscape@plotly.com>
Author-email: cytoscape@plotly.com
License: MIT
Classifier: Environment :: Web Environment
Classifier: Framework :: Flask
Classifier: Intended Audience :: Developers
Classifier: Intended Audience :: Education
Classifier: Intended Audience :: Financial and Insurance Industry
Classifier: Intended Audience :: Healthcare Industry
Classifier: Intended Audience :: Manufacturing
Classifier: Intended Audience :: Science/Research
Classifier: License :: OSI Approved :: MIT License
Classifier: Programming Language :: Python
Classifier: Programming Language :: Python :: 3
Classifier: Programming Language :: Python :: 3.8
Classifier: Programming Language :: Python :: 3.9
Classifier: Programming Language :: Python :: 3.10
Classifier: Programming Language :: Python :: 3.11
Classifier: Programming Language :: Python :: 3.12
Classifier: Topic :: Database :: Front-Ends
Classifier: Topic :: Scientific/Engineering :: Visualization
Classifier: Topic :: Software Development :: Libraries :: Application Frameworks
Requires-Python: >=3.8
License-File: LICENSE
Requires-Dist: dash
Provides-Extra: leaflet
Requires-Dist: dash-leaflet (>=1.0.10) ; extra == 'leaflet'
